LICENSE.txt
MANIFEST.in
README.rst
setup.py
hanyang_registration/__init__.py
hanyang_registration/sugang.py
hanyang_registration.egg-info/PKG-INFO
hanyang_registration.egg-info/SOURCES.txt
hanyang_registration.egg-info/dependency_links.txt
hanyang_registration.egg-info/requires.txt
hanyang_registration.egg-info/top_level.txt