Metadata-Version: 1.0
Name: hanyang-registration
Version: 1.1.3
Summary: Hanyang Class Registration for python
Home-page: https://github.com/Jaram/Hanyang-Class-Registration
Author: Jin-Soo Han, Jaram
Author-email: jinsu0411@gmail.com
License: The MIT License
Keywords: hanyang,registration
Platform: UNKNOWN
